testing_compose_deployment_v0_ti/__init__.py
testing_compose_deployment_v0_ti/api_client.py
testing_compose_deployment_v0_ti/api_response.py
testing_compose_deployment_v0_ti/configuration.py
testing_compose_deployment_v0_ti/exceptions.py
testing_compose_deployment_v0_ti/py.typed
testing_compose_deployment_v0_ti/rest.py
testing_compose_deployment_v0_ti/api/__init__.py
testing_compose_deployment_v0_ti/api/gifs_api.py
testing_compose_deployment_v0_ti/api/stickers_api.py
testing_compose_deployment_v0_ti/models/__init__.py
testing_compose_deployment_v0_ti/models/get_gifs_by_id200_response.py
testing_compose_deployment_v0_ti/models/gif.py
testing_compose_deployment_v0_ti/models/gif_images.py
testing_compose_deployment_v0_ti/models/gif_images_downsized.py
testing_compose_deployment_v0_ti/models/gif_images_downsized_large.py
testing_compose_deployment_v0_ti/models/gif_images_downsized_medium.py
testing_compose_deployment_v0_ti/models/gif_images_downsized_small.py
testing_compose_deployment_v0_ti/models/gif_images_downsized_still.py
testing_compose_deployment_v0_ti/models/gif_images_fixed_height.py
testing_compose_deployment_v0_ti/models/gif_images_fixed_height_downsampled.py
testing_compose_deployment_v0_ti/models/gif_images_fixed_height_small.py
testing_compose_deployment_v0_ti/models/gif_images_fixed_height_small_still.py
testing_compose_deployment_v0_ti/models/gif_images_fixed_height_still.py
testing_compose_deployment_v0_ti/models/gif_images_fixed_width.py
testing_compose_deployment_v0_ti/models/gif_images_fixed_width_downsampled.py
testing_compose_deployment_v0_ti/models/gif_images_fixed_width_small.py
testing_compose_deployment_v0_ti/models/gif_images_fixed_width_small_still.py
testing_compose_deployment_v0_ti/models/gif_images_fixed_width_still.py
testing_compose_deployment_v0_ti/models/gif_images_looping.py
testing_compose_deployment_v0_ti/models/gif_images_original.py
testing_compose_deployment_v0_ti/models/gif_images_original_still.py
testing_compose_deployment_v0_ti-0.0.1.dist-info/METADATA
testing_compose_deployment_v0_ti-0.0.1.dist-info/WHEEL
testing_compose_deployment_v0_ti-0.0.1.dist-info/top_level.txt
testing_compose_deployment_v0_ti-0.0.1.dist-info/RECORD
